LICENSE.rst
MANIFEST.in
README.rst
setup.py
whip/__init__.py
whip/__main__.py
whip/cli.py
whip/db.py
whip/json.py
whip/reader.py
whip/util.py
whip/web.py
whip/wsgi.py
whip.egg-info/PKG-INFO
whip.egg-info/SOURCES.txt
whip.egg-info/dependency_links.txt
whip.egg-info/entry_points.txt
whip.egg-info/requires.txt
whip.egg-info/top_level.txt