Metadata-Version: 1.1
Name: whip
Version: 0.1
Summary: Whip, the who, what, where and when about IP address data
Home-page: https://github.com/wbolster/whip
Author: Wouter Bolsterlee
Author-email: uws@xs4all.nl
License: BSD
Platform: UNKNOWN
Classifier: Development Status :: 4 - Beta
Classifier: License :: OSI Approved :: BSD License
Classifier: Programming Language :: Python
Classifier: Programming Language :: Python :: 3
Classifier: Topic :: Database
